airtest/base.py
airtest/cli2.py
airtest/devsuit.py
airtest/jsonlog.py
airtest/log2html.py
airtest/monitor.py
airtest/patch.py
airtest/watch2html.py
airtest/__init__.py
airtest/__main__.py
airtest/androaxml/androguard.zip
airtest/androaxml/__init__.py
airtest/binfiles/adb-keyboard.apk
airtest/binfiles/airtoolbox
airtest/binfiles/airtoolbox.version
airtest/device/android.py
airtest/device/common.py
airtest/device/dummy.py
airtest/device/ios.py
airtest/device/windows.py
airtest/device/winExample.py
airtest/device/__init__.py
airtest/htmltemplate/app.js
airtest/htmltemplate/highstock-data-cpu.json
airtest/htmltemplate/highstock-data-mem.json
airtest/htmltemplate/index.html
airtest/htmltemplate/css/bootstrap.min.css
airtest/htmltemplate/css/lightbox.css
airtest/htmltemplate/js/bootstrap.min.js
airtest/htmltemplate/js/Chart.js
airtest/htmltemplate/js/highstock.js
airtest/htmltemplate/js/jquery.min.js
airtest/htmltemplate/js/lightbox.min.js
airtest/htmltemplate/js/lightbox.min.map
airtest/image/auto.py
airtest/image/image_SIFT.py
airtest/image/image_template.py
airtest/image/sift.py
airtest/image/template.py
airtest/image/toolbox.py
airtest/image/__init__.py
airtest/watchhtmltemplate/data.js
airtest/watchhtmltemplate/index.html
airtest/watchhtmltemplate/css/bootstrap.min.css
airtest/watchhtmltemplate/css/watch.css
airtest/watchhtmltemplate/js/bootstrap.min.js
airtest/watchhtmltemplate/js/Chart.js
airtest/watchhtmltemplate/js/html5shiv.js
airtest/watchhtmltemplate/js/jquery.min.js
airtest/webgui/__init__.py
airtest/webgui/__init__.pyc
airtest/webgui/routers/api.py
airtest/webgui/routers/api.pyc
airtest/webgui/routers/home.py
airtest/webgui/routers/home.pyc
airtest/webgui/routers/utils.py
airtest/webgui/routers/utils.pyc
airtest/webgui/routers/__init__.py
airtest/webgui/routers/__init__.pyc
airtest/webgui/static/css/bootstrap-theme.css
airtest/webgui/static/css/bootstrap-theme.css.map
airtest_for_h9-0.2.1.9.dist-info/DESCRIPTION.rst
airtest_for_h9-0.2.1.9.dist-info/entry_points.txt
airtest_for_h9-0.2.1.9.dist-info/METADATA
airtest_for_h9-0.2.1.9.dist-info/metadata.json
airtest_for_h9-0.2.1.9.dist-info/RECORD
airtest_for_h9-0.2.1.9.dist-info/top_level.txt
airtest_for_h9-0.2.1.9.dist-info/WHEEL
