Metadata-Version: 2.0
Name: airtest-for-h9
Version: 0.2.1.9
Summary: mobile test(black air) python lib
Home-page: UNKNOWN
Author: zheng wen
Author-email: wenzheng@whu.edu.cn
License: UNKNOWN
Platform: UNKNOWN
Requires-Dist: Appium-Python-Client (>=0.10)
Requires-Dist: click (>=3.3)
Requires-Dist: fuckit (>=4.8.0)
Requires-Dist: humanize (>=0.5)
Requires-Dist: pystache (>=0.5.4)
Requires-Dist: Flask (>=0.10.1)
